basedtyping/__init__.py
basedtyping/py.typed
basedtyping/runtime_only.py
basedtyping/transformer.py
basedtyping/typetime_only.py
basedtyping-0.1.10.dist-info/LICENSE
basedtyping-0.1.10.dist-info/METADATA
basedtyping-0.1.10.dist-info/WHEEL
basedtyping-0.1.10.dist-info/RECORD
