Metadata-Version: 2.1
Name: basedtyping
Version: 0.1.10
Summary: Utilities for basedmypy
Author: DetachHead
Author-email: detachhead@users.noreply.github.com
Requires-Python: >=3.9,<4.0
Classifier: Programming Language :: Python :: 3
Classifier: Programming Language :: Python :: 3.9
Classifier: Programming Language :: Python :: 3.10
Classifier: Programming Language :: Python :: 3.11
Classifier: Programming Language :: Python :: 3.12
Requires-Dist: typing_extensions (>=4.12.2,<5.0.0)
